barrage/__init__.py
barrage/api.py
barrage/config.py
barrage/console.py
barrage/defaults.py
barrage/engine.py
barrage/log.py
barrage/model.py
barrage/schema.json
barrage/services.py
barrage/solver.py
barrage/dataset/__init__.py
barrage/dataset/core.py
barrage/dataset/loader.py
barrage/dataset/transformer.py
barrage/utils/__init__.py
barrage/utils/import_utils.py
barrage/utils/io_utils.py
barrage/utils/tf_utils.py
barrage-0.6.0.dist-info/LICENSE
barrage-0.6.0.dist-info/METADATA
barrage-0.6.0.dist-info/WHEEL
barrage-0.6.0.dist-info/entry_points.txt
barrage-0.6.0.dist-info/top_level.txt
barrage-0.6.0.dist-info/RECORD
