Metadata-Version: 2.1
Name: barrage
Version: 0.6.0
Summary: A supervised deep learning tool.
Home-page: https://github.com/briannemsick/barrage/
Author: Brian Nemsick
Author-email: brian.nemsick@gmail.com
License: MIT
Platform: UNKNOWN
Classifier: Programming Language :: Python
Classifier: Development Status :: 3 - Alpha
Classifier: License :: OSI Approved :: MIT License
Classifier: Topic :: Scientific/Engineering
Classifier: Topic :: Scientific/Engineering :: Artificial Intelligence
Classifier: Topic :: Software Development :: Libraries :: Python Modules
Classifier: Programming Language :: Python :: 3.6
Classifier: Programming Language :: Python :: 3.7
Requires-Python: >=3.6
Requires-Dist: click
Requires-Dist: cytoolz (>=0.9.0)
Requires-Dist: jsonschema (>=3.0)
Requires-Dist: numpy
Requires-Dist: pandas
Requires-Dist: tensorflow (<2.5,>=2.4.0)
Provides-Extra: tests
Requires-Dist: black ; extra == 'tests'
Requires-Dist: codecov ; extra == 'tests'
Requires-Dist: flake8 ; extra == 'tests'
Requires-Dist: flake8-bugbear ; extra == 'tests'
Requires-Dist: flake8-comprehensions ; extra == 'tests'
Requires-Dist: flake8-print ; extra == 'tests'
Requires-Dist: isort ; extra == 'tests'
Requires-Dist: mypy ; extra == 'tests'
Requires-Dist: pre-commit ; extra == 'tests'
Requires-Dist: pre-commit-hooks ; extra == 'tests'
Requires-Dist: pytest ; extra == 'tests'
Requires-Dist: pytest-cov ; extra == 'tests'
